{"body": "\nhi guys\n\n\n\nis there something that can help me to understand why this screen appears when i want to use a ladybug or honeybee comand?\n\n\n\nthanks a lot\n\n\n\nAndrea\u00a0\n", "attachments": [{"link": "http://www.grasshopper3d.com/group/ladybug/forum/attachment/download?id=2985220%3AUploadedFile%3A1670845", "name": "1.png"}], "created_by_name": "Andrea Giglio", "created_at": "January 12, 2017 at 7:29am", "created_by": "AndreaGiglio", "topic": "python problem?", "replies": [{"body": "\nAndrea,\n\nMake sure that you install the GHPython component from here:\n\n[http://www.food4rhino.com/app/ghpython](http://www.food4rhino.com/app/ghpython)\n\n-Chris\n", "attachments": [], "created_by_name": "Chris Mackey", "created_at": "January 12, 2017 at 8:30am", "created_by": "ChrisMackey", "replies": []}], "id": "1670846"}