{"body": "\nHi Chris and Mostapha,\n\n\n\nThanks! I look forward to helping in the development.\n\n\n\nJust one last clarification.\n\nSince Python 3 has been mentioned (and implied that HB[+] can be made do work with Py3+), does that mean that the Rhino team is planning on adding other implementations of Python? (CPython maybe?) (Since Rhino5 is limited to 2.7 because it's using IronPython).\n", "attachments": [], "created_by_name": "Pin", "created_at": "January 30, 2017 at 06:37AM", "created_by": "Pin", "parent_id": "reply_2985220_Comment_1680266", "id": "reply_2985220_Comment_1680883"}