{"body": "\nHi Fahime,\n\nAs mostapha has said you shouldn't attach the light shelf as part of your zone and should be separated.\n\nI attached the revised file to understand better.\n\nbest\n\nMasoome\n", "attachments": [{"link": "http://www.grasshopper3d.com/group/ladybug/forum/attachment/download?id=2985220%3AUploadedFile%3A1365945", "name": "52-msm.gh"}], "created_by_name": "masoome", "created_at": "September 21, 2015 at 11:33am", "created_by": "masoome", "parent_id": "topic_1364771", "id": "reply_2985220_Comment_1365943"}