{"body": "\nIt's happening when you initially create the honeybee zone/surface. If you get an error that transform is not available then the HBObject is created with an older version of Honeybee which is missing this method. Recalculate the file with the new version of Honeybee and it should work with no issues.\n", "attachments": [], "created_by_name": "Mostapha Sadeghipour Roudsari", "created_at": "November 10, 2015 at 9:34am", "created_by": "MostaphaSadeghipour", "parent_id": "reply_2985220_Comment_1393698", "id": "reply_2985220_Comment_1397679"}