{"body": "\nHi Helena,\n\nAttached a file where you can see point 2 working. The reason you get only one hour is because you defined only one hour in the sunpath component.\n\nI updated the file to the last version.\n\nI grouped in white color what i added for your convenience.\n\nDefined one surface to cast shadows. Your geometry is not working for me either.\n\nHope it helps,\n\n-A.\n", "attachments": [{"link": "http://www.grasshopper3d.com/group/ladybug/forum/attachment/download?id=2985220%3AUploadedFile%3A1218138", "name": "ShadowStudy_test_surfaces_AY.gh"}], "created_by_name": "Abraham Yezioro", "created_at": "February 5, 2015 at 12:15pm", "created_by": "AbrahamYezioro", "parent_id": "reply_2985220_Comment_1217803", "id": "reply_2985220_Comment_1218137"}