{"body": "\nHi Elize and Vinu,\n\n\n\nSorry for not getting back sooner I will have a crack at this tonight by adding the functionality that Mostapha suggested to the\u00a0Honeybee_Re-run IDF component. Could either you and Vinu make an example file for me to test this component on?\n\n\n\nSome things might be easier on Skype my time is anton.szilasi I'm in Portugal at the moment but moving to US central time in the next month to 6 weeks.\n", "attachments": [], "created_by_name": "Anton Szilasi", "created_at": "September 29, 2015 at 06:41AM", "created_by": "AntonSzilasi", "parent_id": "reply_2985220_Comment_1367975", "id": "reply_2985220_Comment_1370611"}