{"body": "\nHi Christian,\n\n\n\nIf Djordje Spasic is around on the forums, he is the most qualified to answer this one since he added the functions to calculate PET, which are used both by the Ladybug_Thermal Comfort Indices component and the Honeybee PET comfort map recipes.\n\n\n\n\u00a0For the time being, I can point you to Djordje's contributed code to calculate PET here:\n\n[https://github.com/mostaphaRoudsari/ladybug/blob/master/src/ladybug...](https://github.com/mostaphaRoudsari/ladybug/blob/master/src/ladybug_ladybug.py#L5215-L5511)\n\n\n\nYou see at the top that he references\u00a0Peter Hoeppe so it's looking probable that Ladybug is using the original PET.\n\n-Chris\n", "attachments": [], "created_by_name": "Chris Mackey", "created_at": "August 29, 2017 at 06:44AM", "created_by": "chris", "parent_id": "topic_1805397", "id": "reply_2985220_Comment_1805567"}