{"body": "\nGrasshope,\n\nAgain, I am very sorry for the late reply. \u00a0Hopefully, all of this has been addressed with the new Ground Zone component.\n\nI explained why you needed to set the construction on both of the Set EP Construction components here:\n\n[http://www.grasshopper3d.com/group/ladybug/forum/topics/questions-a...](http://www.grasshopper3d.com/group/ladybug/forum/topics/questions-about-outdoor-microclimate-map)\n\nAs for the reason why re-connection is needed, that is strange indeed! \u00a0My guess it that this resulted from a very old bug in the previous release. \u00a0This seems to be fixed now, as evidenced by my attached failure to replicate the issue.\n\n-Chris\n", "attachments": [{"link": "http://www.grasshopper3d.com/group/ladybug/forum/attachment/download?id=2985220%3AUploadedFile%3A1398594", "name": "AttemptToReplicateError.gh"}], "created_by_name": "Chris Mackey", "created_at": "November 11, 2015 at 02:43PM", "created_by": "chris", "parent_id": "reply_2985220_Comment_1395102", "id": "reply_2985220_Comment_1398592"}