{"body": "\nErnesto,\n\n\n\nThe reason for the different results with the the same simulation is Radiance's stoichastic way of ray-tracing. \u00a0It's still accurate and see these\u00a0[other discussions](http://www.grasshopper3d.com/page/search-results?cx=007664031582976519548%3A0mtws3t01h4&amp;cof=FORID%3A10&amp;ie=UTF-8&amp;q=Stochastic+radiance&amp;sa=Search&amp;siteurl=www.grasshopper3d.com%2F&amp;ref=www.grasshopper3d.com%2Fgroup%2Fladybug%2Fforum%2Ftopic%2Fshow%3Fid%3D2985220%253ATopic%253A1418152%26xg_source%3Dmsg&amp;ss=4922j3167922j15).\n\n\n\n\u00a02C seems pretty reasonable when talking about MRT differences from the sun. \u00a0In many cases you can get MRT differences as large as 20 C between sitting in the sun and sitting in the shade. \u00a0This is the consensus of many experts like those at the thermal comfort research group at the Berkeley Center for the Built Environment, who established the method used here and published to a peer-reviewed scientific journal:\n\n[http://www.sciencedirect.com/science/article/pii/S0360132314002960](http://www.sciencedirect.com/science/article/pii/S0360132314002960)\n\n\n\n-Chris\n", "attachments": [], "created_by_name": "Chris Mackey", "created_at": "October 16, 2016 at 11:11am", "created_by": "chris", "parent_id": "reply_2985220_Comment_1616297", "id": "reply_2985220_Comment_1619297"}