{"body": "\nWhat Sarith\u00a0said. I just checked your example and it runs with no issues.\n\nI attached both .sky and ,call file that should be generated under (C:\\ladybug\\skylib\\cumulativeSkies\\Houston_Ellington_Afb_)\n", "attachments": [{"link": "http://www.grasshopper3d.com/group/ladybug/forum/attachment/download?id=2985220%3AUploadedFile%3A1607413", "name": "cumulativeSky_1_1_1_12_31_24.sky"}, {"link": "http://www.grasshopper3d.com/group/ladybug/forum/attachment/download?id=2985220%3AUploadedFile%3A1607414", "name": "Houston_Ellington_Afb__1.cal"}], "created_by_name": "Mostapha Sadeghipour Roudsari", "created_at": "September 28, 2016 at 7:35am", "created_by": "mostapha", "parent_id": "reply_2985220_Comment_1607133", "id": "reply_2985220_Comment_1607411"}