{"body": "\nThat is what I meant yes. I had too many surface to do this, it requires adding way too much modules and it's hard to find the correct item (is there an actual way aside from trial and error?).\n\n\n\nSo I did like Chris said, I intersected, baked, and did the whole process after that. Hopefully I won't regret it too much once I had to change something :)\n\n\n\nThanks to you both.\n", "attachments": [], "created_by_name": "Julien Marrec", "created_at": "March 24, 2015 at 9:35am", "created_by": "JulienMarrec", "parent_id": "reply_2985220_Comment_1249287", "id": "reply_2985220_Comment_1249295"}