{"body": "\nMostapha,\n\nI've been looking around for E+v8.2 all morning but the site only contains files up to 8.1.0.009 or a link to github for the latest 8.3 version. Where did you get all the 8.2.1--8.2.10 versions?\u00a0\n\n\n\nregards,\u00a0\n\n\n\nM\n\n\n", "attachments": [], "created_by_name": "Mauricio Aguilar Cardenas", "created_at": "July 09, 2015 at 03:43AM", "created_by": "MauricioAguilarCardenas135", "parent_id": "reply_2985220_Comment_1322539", "id": "reply_2985220_Comment_1322835"}