{"body": "\nFederico,\n\nUTCI uses a big 200-term polynomial approximation, which can all be found here:\n\n[https://github.com/mostaphaRoudsari/ladybug/blob/master/src/ladybug...](https://github.com/mostaphaRoudsari/ladybug/blob/master/src/ladybug_ladybug.py#L4043-L4320)\n\nThis polynomial was derived from thousands of simulations with Fiala human energy balance model and survey results of adaptive clothing behavior in the outdoors.\n", "attachments": [], "created_by_name": "Chris Mackey", "created_at": "May 17, 2017 at 12:00pm", "created_by": "ChrisMackey", "parent_id": "topic_1752691", "id": "reply_2985220_Comment_1753131"}