{"body": "\nI still have it in my tab! Something is wrong with your installation. I'm attaching the userobject so you can drag and drop it into canvas.\n", "attachments": [{"link": "http://www.grasshopper3d.com/group/ladybug/forum/attachment/download?id=2985220%3AUploadedFile%3A1813930", "name": "Honeybee_ Run Energy Simulation.ghuser"}], "created_by_name": "Mostapha Sadeghipour Roudsari", "created_at": "September 15, 2017 at 12:20PM", "created_by": "mostapha", "parent_id": "topic_1813626", "id": "reply_2985220_Comment_1813928"}