{"body": "\nI am sorry, I thought I have internalized the geometry.\n\nHere Is the geometry attached.\n\nBtw I have updated the file and components\u00a0through the **HoneyBee_Update HoneyBee** and **LadyBug_Update LadyBug** components, is it right? They are now updated to the FEB_03_2016 is it right??\n\n\n\n\n\n\n", "attachments": [{"link": "http://www.grasshopper3d.com/group/ladybug/forum/attachment/download?id=2985220%3AUploadedFile%3A1555213", "name": "plot.3dm"}], "created_by_name": "Claudia", "created_at": "June 24, 2016 at 8:45am", "created_by": "Claudia598", "parent_id": "reply_2985220_Comment_1555045", "id": "reply_2985220_Comment_1555212"}