{"body": "Ilona,\nI'm not sure 100% but i think the problem might be caused becouse your old python version. The recommended versin can be downloaded from this link:\nhttps://github.com/mcneel/ghpython/releases/download/v0.6.0.3/GhPyt...\nWhich is fully compatible with LB+HB. Can be interesting to hear why you say it isn't.\n-A.", "attachments": [], "created_by_name": "Abraham Yezioro", "created_at": "December 29, 2014 at 11:13AM", "created_by": "AbrahamYezioro", "parent_id": "topic_1195258", "id": "reply_2985220_Comment_1195577"}