{"body": "\nHi architsama,\n\n\n\nWe have added some cool features to Butterfly recently. If you update the component you will be able to have access to them.\n\n\n\nPlease let us know of your experiences with the tool, still a long way to go!\n\n\n\nKind regards,\n\nTheodore.\n", "attachments": [], "created_by_name": "Theodoros Galanos", "created_at": "October 07, 2016 at 03:21AM", "created_by": "TheodorosGalanos", "parent_id": "reply_2985220_Comment_1612833", "id": "reply_2985220_Comment_1612756"}