{"body": "\nAbraham,\u00a0\n\nGreat suggestion on the EMS, I'll give it a go first thing Monday. Thanks!\n\nPhase change materials require a minimum energy load and have variable heat capacitance properties that I currently don't want to consider, but could be useful in a further research sims.\u00a0\n\nbest wishes,\u00a0\n\nMauricio\n\n\n", "attachments": [], "created_by_name": "Mauricio Aguilar Cardenas", "created_at": "February 13, 2016 at 3:32pm", "created_by": "MauricioAguilarCardenas135", "parent_id": "reply_2985220_Comment_1462119", "id": "reply_2985220_Comment_1462204"}