{"body": "Hey Theodore,\nthanks for the reply, but what I actually meant is, if I can use it that way but within grasshopper like in the tutorials. Not just for preparation of the case, but actually starting the simulation. Is it possible to tell butterfly not to use the proposed docker OF but the regular OF either of the host system or of a remote machine for running the meshing and solver commands?\nThanks", "attachments": [], "created_by_name": "Albert Pressler", "created_at": "March 25, 2017 at 02:54AM", "created_by": "AlbertPressler", "parent_id": "topic_1719706", "id": "reply_2985220_Comment_1720530"}