{"body": "\nSorry Abraham,\n\n\n\nLong night. You are right of course. You can find the file in this discussion.\n\n\n\n[http://www.grasshopper3d.com/group/ladybug/forum/topics/energy-shad...](http://www.grasshopper3d.com/group/ladybug/forum/topics/energy-shade-benefit-evaluation)\n\n\n\nKind regards,\n\nTheodore.\n", "attachments": [], "created_by_name": "Theodoros Galanos", "created_at": "February 16, 2015 at 9:43pm", "created_by": "TheodorosGalanos", "parent_id": "reply_2985220_Comment_1225286", "id": "reply_2985220_Comment_1225891"}