{"body": "\nI should add that a workflow for natural ventilation will be available at some point. We are still not sure what is the best way of addressing natural ventilation. You can read more here and there is an email chain going on:\u00a0[https://github.com/mostaphaRoudsari/Honeybee/issues/134](https://github.com/mostaphaRoudsari/Honeybee/issues/134)\n", "attachments": [], "created_by_name": "Mostapha Sadeghipour Roudsari", "created_at": "December 9, 2014 at 7:33pm", "created_by": "mostapha", "parent_id": "reply_2985220_Comment_1184478", "id": "reply_2985220_Comment_1184835"}