{"body": "\nChristian,\n\nI was browsing through the EnergyPlus reference and I realized that there may be a simpler way to get a dynamic U-Value with this object:\n\n[http://bigladdersoftware.com/epx/docs/8-0/input-output-reference/pa...](http://bigladdersoftware.com/epx/docs/8-0/input-output-reference/page-010.html#materialpropertyvariablethermalconductivity)\n\nI don't have time to fully test it out now but I would suggest looking there before going for the EMS option.\n\n-Chris\n", "attachments": [], "created_by_name": "Chris Mackey", "created_at": "December 13, 2015 at 10:11PM", "created_by": "chris", "parent_id": "reply_2985220_Comment_1420783", "id": "reply_2985220_Comment_1420679"}