{"body": "\nThank you, Abraham. \u00a0You saved me some time with running the update. \u00a0I just updated the download link at the hydra page to have your file.\n\nI apologize that all of my hydra files are not up to date. \u00a0I'll do another sweeping update after the next stable release of LB+HB.\n\n-Chris\n", "attachments": [], "created_by_name": "Chris Mackey", "created_at": "December 6, 2016 at 5:58am", "created_by": "ChrisMackey", "parent_id": "reply_2985220_Comment_1652988", "id": "reply_2985220_Comment_1652892"}