{"body": "\n[<img class=\"align-full\" src=\"http://api.ning.com:80/files/oto4-hHdKDEa94fP*1UTBVVQrZWscN1bHW3kn6Es3O-6Ec2qdiUmXZ2x1I2KL2uhrnlt7fjVha3cXVX5qD-54CSkuTJm3gxO/Canvasat130820.png?width=721\" width=\"721\"/>](http://api.ning.com:80/files/oto4-hHdKDEa94fP*1UTBVVQrZWscN1bHW3kn6Es3O-6Ec2qdiUmXZ2x1I2KL2uhrnlt7fjVha3cXVX5qD-54CSkuTJm3gxO/Canvasat130820.png)Ok I managed to update and get started again (lots of changes in HB) The components solved the previous problems but I get windows where the 2 volumes touch (party wall). There shouldn't be there. I've updated the files.\n\n\n", "attachments": [], "created_by_name": "Claudio", "created_at": "July 05, 2014 at 11:11AM", "created_by": "Claudio", "parent_id": "reply_2985220_Comment_1098038", "id": "reply_2985220_Comment_1098130"}