{"body": "\nThanks Mostapha. stp is geometry - OpenCascade, stl is mesh file format. Anyways.\n\nWhat are the geometry files format that would work without a problem, imported from other standard CAD packages?\n\nAttaching the lpt.stp (OpenCascade Geometry) that I want to work with.\n\nHere is the log of MeshToNURB and MergeAllFaces on the attached file\n\nCommand: MeshToNURB<br/>Select polygon meshes to convert to NURBS ( TrimTriangularFaces=Yes ):<br/>3 polysurfaces added to selection.<br/>Command: MeshToNURB<br/>Select polygon meshes to convert to NURBS ( TrimTriangularFaces=Yes ):<br/>Select polygon meshes to convert to NURBS ( TrimTriangularFaces=Yes ):<br/>Command: MergeAllFaces<br/>Select a Polysurface:<br/>Select a Polysurface. Press Enter when done:<br/>Unable to move edges within face tolerance, nothing done<br/>Unable to move edges within face tolerance, nothing done<br/>Unable to move edges within face tolerance, nothing done<br/>Unable to move edges within face tolerance, nothing done<br/><br/>Merged 1 polysurface. 2 polysurfaces could not be merged further.<br/>Command: MergeAllFaces\n\nI want to see 3 volumes from this file in the Brep object.\n\nMany thanks.\n", "attachments": [{"link": "http://www.grasshopper3d.com/group/ladybug/forum/attachment/download?id=2985220%3AUploadedFile%3A1667866", "name": "lpt.stp"}], "created_by_name": "Rajeev Jain", "created_at": "January 06, 2017 at 04:15PM", "created_by": "RajeevJain", "parent_id": "reply_2985220_Comment_1668012", "id": "reply_2985220_Comment_1667865"}