{"body": "\nI'm not sure if you're trying to find the direct radiation as the title of your question says or the amount which is reflected from other buildings which is what I understand from the first paragraph.\n\nIn any case, if you apply a fully black material to buildings and set ab to 0 then you will get only direct radiation as radiance won't calculate any of the ambient bounces.\n\nNow you can subtract the values of the analysis with normal setting from this one to find the reflected values.\n\nMostapha\n", "attachments": [], "created_by_name": "Mostapha Sadeghipour Roudsari", "created_at": "January 23, 2016 at 6:12pm", "created_by": "mostapha", "parent_id": "topic_1445008", "id": "reply_2985220_Comment_1445773"}