{"body": "\nThanks Alejandro! I added it here ([https://github.com/mostaphaRoudsari/Honeybee/issues/222#issuecommen...](https://github.com/mostaphaRoudsari/Honeybee/issues/222#issuecomment-122328325))\u00a0so Chien Si can get back to you soon. Sorry for the delay!\n", "attachments": [], "created_by_name": "Mostapha Sadeghipour Roudsari", "created_at": "July 17, 2015 at 10:08am", "created_by": "MostaphaSadeghipour", "parent_id": "reply_2985220_Comment_1324495", "id": "reply_2985220_Comment_1327573"}