{"body": "\nMostapha and Chris,\n\n\n\nI am using the SET Comfort component from your YouTube presentation,\u00a0but when I plug-in a Analysis Period larger than 5 months the component crashes and the error balloon says: \"1. The calculation has been terminated by the user!\"\n\n\n\nSame behavior if I don t plug-in any Analysis Period.\n\n\n\nIs that a bug or some other logical limitation?\n\n\n\nI attach the relevant images and GH file.\n\n\n\nThanks!\n\n\n\nDimitris\n\n\n", "attachments": [{"link": "http://www.grasshopper3d.com/group/ladybug/forum/attachment/download?id=2985220%3AUploadedFile%3A1232361", "name": "SET_Temp_1.jpg"}, {"link": "http://www.grasshopper3d.com/group/ladybug/forum/attachment/download?id=2985220%3AUploadedFile%3A1232362", "name": "SET_Temp_2.jpg"}, {"link": "http://www.grasshopper3d.com/group/ladybug/forum/attachment/download?id=2985220%3AUploadedFile%3A1232363", "name": "Comfort_Outdoor_SET_01.gh"}], "created_by_name": "Dimitrios Papadopoulos", "created_at": "February 26, 2015 at 11:36am", "created_by": "doompop", "topic": "SET Comfort error when analysis period grater than 5 months.", "id": "topic_1232364"}