{"body": "\nHi everyone,\n\n\n\nJust a sanity check. Is my interior wall orientation crucial to energy simulation in multi zone models (you know the slight discolouration in the Rhino/Grasshoper brep preview)?\n\n\n\nI would hope it isn't as it is a mindbong manual labour to orient everything one by one :(\n\n\n\nKind regards,\n\nTheodore.\n", "attachments": [], "created_by_name": "Theodoros Galanos", "created_at": "April 24, 2015 at 04:01AM", "created_by": "TheodorosGalanos", "topic": "Significance of wall orientation", "id": "topic_1272017"}