{"body": "\nI am trying to import an existing idf geometry file from Openstudio and everytime I look at the model in Rhino, the rooms are on-top of one another.\n\nI tried importing a few idf files from the EPlus example directory and from DesignBuilder, both work much better and give geometry that matches the layout of thermal zones.\n\nIs there anything I am missing in my model? or in how the import idf function works?\n\n\n", "attachments": [{"link": "http://www.grasshopper3d.com/group/ladybug/forum/attachment/download?id=2985220%3AUploadedFile%3A1184801", "name": "openstudio.PNG"}, {"link": "http://www.grasshopper3d.com/group/ladybug/forum/attachment/download?id=2985220%3AUploadedFile%3A1184802", "name": "rhino 3D.PNG"}, {"link": "http://www.grasshopper3d.com/group/ladybug/forum/attachment/download?id=2985220%3AUploadedFile%3A1184803", "name": "exported from OS 2.idf"}], "created_by_name": "Neil Bulger", "created_at": "December 9, 2014 at 11:01pm", "created_by": "NeilBulger", "topic": "Geometry Import from Openstudio", "id": "topic_1184804"}