{"body": "\nThe\u00a0Ladybug_Shading Mask component allows to define the Sky View Factor starting from a 3D model.\n\nThe\u00a0[Rayman software](http://link.springer.com/article/10.1007/s00484-006-0061-8)\u00a0or [other\u00a0sw](http://link.springer.com/article/10.1007/s00704-011-0402-3)\u00a0allow to do the same starting\u00a0from a real image captured with a fish-eye.\n\nI have seen if in ladybug there is a specific component but I have not found it. So I ask: \"have you considered to implement this features in ladybug?\"\n\n\n\nRegards,\n\nFrancesco\n", "attachments": [], "created_by_name": "Francesco", "created_at": "December 6, 2016 at 6:45am", "created_by": "Francesco897", "topic": "Sky View Factor calculation: different possible approaches.", "id": "topic_1652894"}