{"body": "\nHi,everyone.\n\n\n\nI try to export png image using \"view from sun\".<br/>This component indicates overall view,but T want to set my magnification like upload image(idealimage).<br/>I think I can set a magnification on grasshopper python script,but I can't understand this script.<br/>If I can set any magnification or lock magnification, please tell me how to do it.\n\n\n\ntaizo\n", "attachments": [{"link": "http://www.grasshopper3d.com/group/ladybug/forum/attachment/download?id=2985220%3AUploadedFile%3A1646794", "name": "viewfromsum.3dm"}, {"link": "http://www.grasshopper3d.com/group/ladybug/forum/attachment/download?id=2985220%3AUploadedFile%3A1646795", "name": "exsunpossim.gh"}, {"link": "http://www.grasshopper3d.com/group/ladybug/forum/attachment/download?id=2985220%3AUploadedFile%3A1646796", "name": "idealimage.PNG"}], "created_by_name": "taizo shimo", "created_at": "November 27, 2016 at 12:29PM", "created_by": "taizoshimo", "topic": "magnification of \"view from sun\"", "id": "topic_1646797"}