{"body": "\nI want to share with you our last article: **Design and Development of a Nearable Wireless System to Control Indoor Air Quality and Indoor Lighting Quality**. As you can see from the links below, we have used ladybug tools to display the results of the test in a real office.\u00a0You can read the paper in open access format directly from\u00a0[the web page of the editor](http://www.mdpi.com/1424-8220/17/5/1021)\u00a0or from my\u00a0[researchgate web page](https://www.researchgate.net/publication/316668077_Design_and_Development_of_a_Nearable_Wireless_System_to_Control_Indoor_Air_Quality_and_Indoor_Lighting_Quality?_iepl%5BviewId%5D=ONvaJv7Z64lNoA1fBUEOYBai&amp;_iepl%5BprofilePublicationItemVariant%5D=default&amp;_iepl%5Bcontexts%5D%5B0%5D=prfpi&amp;_iepl%5BinteractionType%5D=publicationTitle).\n\n\n\nAre you interested or are you involved in the design and development of new solution for\u00a0building automation? Let's \u00a0talk about it.\n\n\u00a0\n\nRegards,\n\nFrancesco.\n", "attachments": [], "created_by_name": "Francesco", "created_at": "May 4, 2017 at 7:07am", "created_by": "Francesco897", "topic": "Ladybug tools and monitoring of a \"smart\" object", "id": "topic_1745488"}