{"body": "\nHi,\n\nhow can I change the color of simulation to black and white?[<img class=\"align-full\" src=\"http://api.ning.com:80/files/SNF651yU0cUVgww6dH*12Eznz5eBrjkyVb74FlFH5c8xomF73s9mc8*AoZTO0SjZQCbagJsgABnTgoam0BXpqjfFHHmwB3Ah/5.png?width=750\" width=\"750\"/>](http://api.ning.com:80/files/SNF651yU0cUVgww6dH*12Eznz5eBrjkyVb74FlFH5c8xomF73s9mc8*AoZTO0SjZQCbagJsgABnTgoam0BXpqjfFHHmwB3Ah/5.png)\n", "attachments": [], "created_by_name": "sajad shahin", "created_at": "March 29, 2016 at 8:11am", "created_by": "sajadshahin", "topic": "change color", "id": "topic_1495162"}