{"body": "\nHi everyone,\n\n\n\nI have a question regarding the calculation of the mean radiant temperature from the \"MicroclimateMap\" component.\n\n\n\nDoes the MRT from this component take into account the solar reflected radiation from the surrounding buildings ?\n\n\n\nThank you for your help and your answers.\n\nHAMDANI El Mehdi\n", "attachments": [], "created_by_name": "Mehdi HAMDANI", "created_at": "July 24, 2017 at 06:41AM", "created_by": "MehdiHAMDANI", "topic": "Solar reflection for mean radiant temperature", "id": "topic_1787985"}