{"body": "\nis it possible to get the output (H/C/F) per zone and not total building energy for each category? I'm developing a matrix for building orientation and am able to get branched data for the other outputs, but the ones listed above are an hourly summary. Using VAV with reheat.\n\n<br/>thanks!\n\n<br/>joel\n", "attachments": [{"link": "http://www.grasshopper3d.com/group/ladybug/forum/attachment/download?id=2985220%3AUploadedFile%3A1480844", "name": "honeybee branched data.jpg"}], "created_by_name": "Joel Yow", "created_at": "March 09, 2016 at 04:30PM", "created_by": "JoelYow", "topic": "Heating/Cooling/Fan Energy by zone for central OpenStudio systems", "id": "topic_1480845"}