{"body": "\nMay I ask if there is a way to save the honeybee thermal zones with adjacency solved, which may take a long time for large model, zone program, loads, etc., all defined so as to save the time to open the file next time or reuse it for different workflow?\n\n\n\nThanks!\n\n\n\n\n", "attachments": [], "created_by_name": "Grasshope", "created_at": "February 5, 2016 at 12:01pm", "created_by": "Grasshope", "topic": "[WIP] is there a way to save fully specified honeybee thermal zones in a component for reuse?", "id": "topic_1455604"}