{"body": "\nFor example, in a kitchen there are different equipment and each of them may have its own schedule.\n\n\n\nSo, may I ask how to assign multiple zone loads and schedules to one zone, especially linking the loads of an equipment to its operation schedule?\n\n\n\nThanks!\n", "attachments": [], "created_by_name": "Grasshope", "created_at": "August 29, 2015 at 10:05am", "created_by": "Grasshope", "topic": "how to assign multiple loads and schedules to a single zone?", "id": "topic_1351044"}